{
  "version": "5",
  "dialect": "mysql",
  "id": "0b4cd72f-7e26-4ff7-9764-a5919452b591",
  "prevId": "3ba9eb25-fd34-4e0b-9244-64d1aa446c66",
  "tables": {
    "handComments": {
      "name": "handComments",
      "columns": {
        "id": {
          "name": "id",
          "type": "int",
          "primaryKey": false,
          "notNull": true,
          "autoincrement": true
        },
        "handId": {
          "name": "handId",
          "type": "int",
          "primaryKey": false,
          "notNull": true,
          "autoincrement": false
        },
        "userId": {
          "name": "userId",
          "type": "int",
          "primaryKey": false,
          "notNull": true,
          "autoincrement": false
        },
        "userName": {
          "name": "userName",
          "type": "varchar(255)",
          "primaryKey": false,
          "notNull": true,
          "autoincrement": false
        },
        "content": {
          "name": "content",
          "type": "text",
          "primaryKey": false,
          "notNull": true,
          "autoincrement": false
        },
        "createdAt": {
          "name": "createdAt",
          "type": "timestamp",
          "primaryKey": false,
          "notNull": true,
          "autoincrement": false,
          "default": "(now())"
        },
        "updatedAt": {
          "name": "updatedAt",
          "type": "timestamp",
          "primaryKey": false,
          "notNull": true,
          "autoincrement": false,
          "onUpdate": true,
          "default": "(now())"
        }
      },
      "indexes": {},
      "foreignKeys": {},
      "compositePrimaryKeys": {
        "handComments_id": {
          "name": "handComments_id",
          "columns": [
            "id"
          ]
        }
      },
      "uniqueConstraints": {},
      "checkConstraint": {}
    },
    "handUpvotes": {
      "name": "handUpvotes",
      "columns": {
        "id": {
          "name": "id",
          "type": "int",
          "primaryKey": false,
          "notNull": true,
          "autoincrement": true
        },
        "handId": {
          "name": "handId",
          "type": "int",
          "primaryKey": false,
          "notNull": true,
          "autoincrement": false
        },
        "userId": {
          "name": "userId",
          "type": "int",
          "primaryKey": false,
          "notNull": true,
          "autoincrement": false
        },
        "createdAt": {
          "name": "createdAt",
          "type": "timestamp",
          "primaryKey": false,
          "notNull": true,
          "autoincrement": false,
          "default": "(now())"
        }
      },
      "indexes": {},
      "foreignKeys": {},
      "compositePrimaryKeys": {
        "handUpvotes_id": {
          "name": "handUpvotes_id",
          "columns": [
            "id"
          ]
        }
      },
      "uniqueConstraints": {},
      "checkConstraint": {}
    },
    "hands": {
      "name": "hands",
      "columns": {
        "id": {
          "name": "id",
          "type": "int",
          "primaryKey": false,
          "notNull": true,
          "autoincrement": true
        },
        "userId": {
          "name": "userId",
          "type": "int",
          "primaryKey": false,
          "notNull": true,
          "autoincrement": false
        },
        "title": {
          "name": "title",
          "type": "varchar(255)",
          "primaryKey": false,
          "notNull": false,
          "autoincrement": false
        },
        "description": {
          "name": "description",
          "type": "text",
          "primaryKey": false,
          "notNull": false,
          "autoincrement": false
        },
        "smallBlind": {
          "name": "smallBlind",
          "type": "int",
          "primaryKey": false,
          "notNull": true,
          "autoincrement": false
        },
        "bigBlind": {
          "name": "bigBlind",
          "type": "int",
          "primaryKey": false,
          "notNull": true,
          "autoincrement": false
        },
        "ante": {
          "name": "ante",
          "type": "int",
          "primaryKey": false,
          "notNull": true,
          "autoincrement": false,
          "default": 0
        },
        "heroPosition": {
          "name": "heroPosition",
          "type": "enum('UTG','UTG+1','UTG+2','MP','MP+1','CO','BTN','SB','BB')",
          "primaryKey": false,
          "notNull": true,
          "autoincrement": false
        },
        "heroCard1": {
          "name": "heroCard1",
          "type": "varchar(3)",
          "primaryKey": false,
          "notNull": true,
          "autoincrement": false
        },
        "heroCard2": {
          "name": "heroCard2",
          "type": "varchar(3)",
          "primaryKey": false,
          "notNull": true,
          "autoincrement": false
        },
        "flopCard1": {
          "name": "flopCard1",
          "type": "varchar(3)",
          "primaryKey": false,
          "notNull": false,
          "autoincrement": false
        },
        "flopCard2": {
          "name": "flopCard2",
          "type": "varchar(3)",
          "primaryKey": false,
          "notNull": false,
          "autoincrement": false
        },
        "flopCard3": {
          "name": "flopCard3",
          "type": "varchar(3)",
          "primaryKey": false,
          "notNull": false,
          "autoincrement": false
        },
        "turnCard": {
          "name": "turnCard",
          "type": "varchar(3)",
          "primaryKey": false,
          "notNull": false,
          "autoincrement": false
        },
        "riverCard": {
          "name": "riverCard",
          "type": "varchar(3)",
          "primaryKey": false,
          "notNull": false,
          "autoincrement": false
        },
        "actions": {
          "name": "actions",
          "type": "json",
          "primaryKey": false,
          "notNull": true,
          "autoincrement": false
        },
        "overallRating": {
          "name": "overallRating",
          "type": "decimal(3,1)",
          "primaryKey": false,
          "notNull": false,
          "autoincrement": false
        },
        "preflopRating": {
          "name": "preflopRating",
          "type": "decimal(3,1)",
          "primaryKey": false,
          "notNull": false,
          "autoincrement": false
        },
        "flopRating": {
          "name": "flopRating",
          "type": "decimal(3,1)",
          "primaryKey": false,
          "notNull": false,
          "autoincrement": false
        },
        "turnRating": {
          "name": "turnRating",
          "type": "decimal(3,1)",
          "primaryKey": false,
          "notNull": false,
          "autoincrement": false
        },
        "riverRating": {
          "name": "riverRating",
          "type": "decimal(3,1)",
          "primaryKey": false,
          "notNull": false,
          "autoincrement": false
        },
        "mistakeTags": {
          "name": "mistakeTags",
          "type": "json",
          "primaryKey": false,
          "notNull": false,
          "autoincrement": false
        },
        "analysis": {
          "name": "analysis",
          "type": "text",
          "primaryKey": false,
          "notNull": false,
          "autoincrement": false
        },
        "aiAnalysis": {
          "name": "aiAnalysis",
          "type": "text",
          "primaryKey": false,
          "notNull": false,
          "autoincrement": false
        },
        "shareToken": {
          "name": "shareToken",
          "type": "varchar(32)",
          "primaryKey": false,
          "notNull": false,
          "autoincrement": false
        },
        "isPublic": {
          "name": "isPublic",
          "type": "int",
          "primaryKey": false,
          "notNull": true,
          "autoincrement": false,
          "default": 0
        },
        "upvoteCount": {
          "name": "upvoteCount",
          "type": "int",
          "primaryKey": false,
          "notNull": true,
          "autoincrement": false,
          "default": 0
        },
        "commentCount": {
          "name": "commentCount",
          "type": "int",
          "primaryKey": false,
          "notNull": true,
          "autoincrement": false,
          "default": 0
        },
        "createdAt": {
          "name": "createdAt",
          "type": "timestamp",
          "primaryKey": false,
          "notNull": true,
          "autoincrement": false,
          "default": "(now())"
        },
        "updatedAt": {
          "name": "updatedAt",
          "type": "timestamp",
          "primaryKey": false,
          "notNull": true,
          "autoincrement": false,
          "onUpdate": true,
          "default": "(now())"
        }
      },
      "indexes": {},
      "foreignKeys": {},
      "compositePrimaryKeys": {
        "hands_id": {
          "name": "hands_id",
          "columns": [
            "id"
          ]
        }
      },
      "uniqueConstraints": {
        "hands_shareToken_unique": {
          "name": "hands_shareToken_unique",
          "columns": [
            "shareToken"
          ]
        }
      },
      "checkConstraint": {}
    },
    "mistakePatterns": {
      "name": "mistakePatterns",
      "columns": {
        "id": {
          "name": "id",
          "type": "int",
          "primaryKey": false,
          "notNull": true,
          "autoincrement": true
        },
        "userId": {
          "name": "userId",
          "type": "int",
          "primaryKey": false,
          "notNull": true,
          "autoincrement": false
        },
        "mistakeType": {
          "name": "mistakeType",
          "type": "varchar(100)",
          "primaryKey": false,
          "notNull": true,
          "autoincrement": false
        },
        "mistakeLabel": {
          "name": "mistakeLabel",
          "type": "varchar(255)",
          "primaryKey": false,
          "notNull": true,
          "autoincrement": false
        },
        "occurrenceCount": {
          "name": "occurrenceCount",
          "type": "int",
          "primaryKey": false,
          "notNull": true,
          "autoincrement": false,
          "default": 1
        },
        "handIds": {
          "name": "handIds",
          "type": "json",
          "primaryKey": false,
          "notNull": false,
          "autoincrement": false
        },
        "firstOccurrence": {
          "name": "firstOccurrence",
          "type": "timestamp",
          "primaryKey": false,
          "notNull": true,
          "autoincrement": false,
          "default": "(now())"
        },
        "lastOccurrence": {
          "name": "lastOccurrence",
          "type": "timestamp",
          "primaryKey": false,
          "notNull": true,
          "autoincrement": false,
          "default": "(now())"
        }
      },
      "indexes": {},
      "foreignKeys": {},
      "compositePrimaryKeys": {
        "mistakePatterns_id": {
          "name": "mistakePatterns_id",
          "columns": [
            "id"
          ]
        }
      },
      "uniqueConstraints": {},
      "checkConstraint": {}
    },
    "userStats": {
      "name": "userStats",
      "columns": {
        "id": {
          "name": "id",
          "type": "int",
          "primaryKey": false,
          "notNull": true,
          "autoincrement": true
        },
        "userId": {
          "name": "userId",
          "type": "int",
          "primaryKey": false,
          "notNull": true,
          "autoincrement": false
        },
        "totalHands": {
          "name": "totalHands",
          "type": "int",
          "primaryKey": false,
          "notNull": true,
          "autoincrement": false,
          "default": 0
        },
        "averageRating": {
          "name": "averageRating",
          "type": "decimal(3,1)",
          "primaryKey": false,
          "notNull": false,
          "autoincrement": false
        },
        "avgPreflopRating": {
          "name": "avgPreflopRating",
          "type": "decimal(3,1)",
          "primaryKey": false,
          "notNull": false,
          "autoincrement": false
        },
        "avgFlopRating": {
          "name": "avgFlopRating",
          "type": "decimal(3,1)",
          "primaryKey": false,
          "notNull": false,
          "autoincrement": false
        },
        "avgTurnRating": {
          "name": "avgTurnRating",
          "type": "decimal(3,1)",
          "primaryKey": false,
          "notNull": false,
          "autoincrement": false
        },
        "avgRiverRating": {
          "name": "avgRiverRating",
          "type": "decimal(3,1)",
          "primaryKey": false,
          "notNull": false,
          "autoincrement": false
        },
        "topMistakes": {
          "name": "topMistakes",
          "type": "json",
          "primaryKey": false,
          "notNull": false,
          "autoincrement": false
        },
        "updatedAt": {
          "name": "updatedAt",
          "type": "timestamp",
          "primaryKey": false,
          "notNull": true,
          "autoincrement": false,
          "onUpdate": true,
          "default": "(now())"
        }
      },
      "indexes": {},
      "foreignKeys": {},
      "compositePrimaryKeys": {
        "userStats_id": {
          "name": "userStats_id",
          "columns": [
            "id"
          ]
        }
      },
      "uniqueConstraints": {
        "userStats_userId_unique": {
          "name": "userStats_userId_unique",
          "columns": [
            "userId"
          ]
        }
      },
      "checkConstraint": {}
    },
    "users": {
      "name": "users",
      "columns": {
        "id": {
          "name": "id",
          "type": "int",
          "primaryKey": false,
          "notNull": true,
          "autoincrement": true
        },
        "openId": {
          "name": "openId",
          "type": "varchar(64)",
          "primaryKey": false,
          "notNull": true,
          "autoincrement": false
        },
        "name": {
          "name": "name",
          "type": "text",
          "primaryKey": false,
          "notNull": false,
          "autoincrement": false
        },
        "email": {
          "name": "email",
          "type": "varchar(320)",
          "primaryKey": false,
          "notNull": false,
          "autoincrement": false
        },
        "loginMethod": {
          "name": "loginMethod",
          "type": "varchar(64)",
          "primaryKey": false,
          "notNull": false,
          "autoincrement": false
        },
        "role": {
          "name": "role",
          "type": "enum('user','admin')",
          "primaryKey": false,
          "notNull": true,
          "autoincrement": false,
          "default": "'user'"
        },
        "createdAt": {
          "name": "createdAt",
          "type": "timestamp",
          "primaryKey": false,
          "notNull": true,
          "autoincrement": false,
          "default": "(now())"
        },
        "updatedAt": {
          "name": "updatedAt",
          "type": "timestamp",
          "primaryKey": false,
          "notNull": true,
          "autoincrement": false,
          "onUpdate": true,
          "default": "(now())"
        },
        "lastSignedIn": {
          "name": "lastSignedIn",
          "type": "timestamp",
          "primaryKey": false,
          "notNull": true,
          "autoincrement": false,
          "default": "(now())"
        }
      },
      "indexes": {},
      "foreignKeys": {},
      "compositePrimaryKeys": {
        "users_id": {
          "name": "users_id",
          "columns": [
            "id"
          ]
        }
      },
      "uniqueConstraints": {
        "users_openId_unique": {
          "name": "users_openId_unique",
          "columns": [
            "openId"
          ]
        }
      },
      "checkConstraint": {}
    }
  },
  "views": {},
  "_meta": {
    "schemas": {},
    "tables": {},
    "columns": {}
  },
  "internal": {
    "tables": {},
    "indexes": {}
  }
}